{
  "reference": "W56197520",
  "pieceId": "1",
  "sourceCnc": "SCARA/OUT_cnc/ID1_W56197520.cnc",
  "boundingBox": [
    [
      0.0,
      0.0
    ],
    [
      111.26,
      0.0
    ],
    [
      111.26,
      235.12
    ],
    [
      0.0,
      235.12
    ]
  ],
  "angle": 0,
  "computable": 1,
  "toolLocation": [],
  "toolActive": [],
  "thickness": 3.0,
  "material": "Acero al carbono N2",
  "geometry": {
    "totalContours": 6,
    "contours": [
      {
        "totalSegments": 7,
        "type": 1,
        "sense": -1,
        "segments": [
          {
            "type": 1,
            "initialPos": [
              27.22,
              20.36
            ],
            "finalPos": [
              28.830000000000005,
              23.15
            ],
            "arcCenter": [
              27.22,
              20.36
            ],
            "arcCenterOff": [
              0.0,
              0.0
            ],
            "arcSense": 0
          },
          {
            "type": 1,
            "initialPos": [
              28.830000000000005,
              23.15
            ],
            "finalPos": [
              35.29,
              23.15
            ],
            "arcCenter": [
              28.830000000000005,
              23.15
            ],
            "arcCenterOff": [
              0.0,
              0.0
            ],
            "arcSense": 0
          },
          {
            "type": 1,
            "initialPos": [
              35.29,
              23.15
            ],
            "finalPos": [
              38.510000000000005,
              17.56
            ],
            "arcCenter": [
              35.29,
              23.15
            ],
            "arcCenterOff": [
              0.0,
              0.0
            ],
            "arcSense": 0
          },
          {
            "type": 1,
            "initialPos": [
              38.510000000000005,
              17.56
            ],
            "finalPos": [
              35.29,
              11.969999999999999
            ],
            "arcCenter": [
              38.510000000000005,
              17.56
            ],
            "arcCenterOff": [
              0.0,
              0.0
            ],
            "arcSense": 0
          },
          {
            "type": 1,
            "initialPos": [
              35.29,
              11.969999999999999
            ],
            "finalPos": [
              28.830000000000005,
              11.969999999999999
            ],
            "arcCenter": [
              35.29,
              11.969999999999999
            ],
            "arcCenterOff": [
              0.0,
              0.0
            ],
            "arcSense": 0
          },
          {
            "type": 1,
            "initialPos": [
              28.830000000000005,
              11.969999999999999
            ],
            "finalPos": [
              25.61,
              17.56
            ],
            "arcCenter": [
              28.830000000000005,
              11.969999999999999
            ],
            "arcCenterOff": [
              0.0,
              0.0
            ],
            "arcSense": 0
          },
          {
            "type": 1,
            "initialPos": [
              25.61,
              17.56
            ],
            "finalPos": [
              27.22,
              20.36
            ],
            "arcCenter": [
              25.61,
              17.56
            ],
            "arcCenterOff": [
              0.0,
              0.0
            ],
            "arcSense": 0
          }
        ]
      },
      {
        "totalSegments": 7,
        "type": 1,
        "sense": -1,
        "segments": [
          {
            "type": 1,
            "initialPos": [
              57.22,
              20.36
            ],
            "finalPos": [
              58.83,
              23.15
            ],
            "arcCenter": [
              57.22,
              20.36
            ],
            "arcCenterOff": [
              0.0,
              0.0
            ],
            "arcSense": 0
          },
          {
            "type": 1,
            "initialPos": [
              58.83,
              23.15
            ],
            "finalPos": [
              65.29,
              23.15
            ],
            "arcCenter": [
              58.83,
              23.15
            ],
            "arcCenterOff": [
              0.0,
              0.0
            ],
            "arcSense": 0
          },
          {
            "type": 1,
            "initialPos": [
              65.29,
              23.15
            ],
            "finalPos": [
              68.51,
              17.56
            ],
            "arcCenter": [
              65.29,
              23.15
            ],
            "arcCenterOff": [
              0.0,
              0.0
            ],
            "arcSense": 0
          },
          {
            "type": 1,
            "initialPos": [
              68.51,
              17.56
            ],
            "finalPos": [
              65.29,
              11.969999999999999
            ],
            "arcCenter": [
              68.51,
              17.56
            ],
            "arcCenterOff": [
              0.0,
              0.0
            ],
            "arcSense": 0
          },
          {
            "type": 1,
            "initialPos": [
              65.29,
              11.969999999999999
            ],
            "finalPos": [
              58.83,
              11.969999999999999
            ],
            "arcCenter": [
              65.29,
              11.969999999999999
            ],
            "arcCenterOff": [
              0.0,
              0.0
            ],
            "arcSense": 0
          },
          {
            "type": 1,
            "initialPos": [
              58.83,
              11.969999999999999
            ],
            "finalPos": [
              55.61,
              17.56
            ],
            "arcCenter": [
              58.83,
              11.969999999999999
            ],
            "arcCenterOff": [
              0.0,
              0.0
            ],
            "arcSense": 0
          },
          {
            "type": 1,
            "initialPos": [
              55.61,
              17.56
            ],
            "finalPos": [
              57.22,
              20.36
            ],
            "arcCenter": [
              55.61,
              17.56
            ],
            "arcCenterOff": [
              0.0,
              0.0
            ],
            "arcSense": 0
          }
        ]
      },
      {
        "totalSegments": 5,
        "type": 0,
        "sense": 1,
        "segments": [
          {
            "type": 3,
            "initialPos": [
              42.06,
              190.0
            ],
            "finalPos": [
              27.120000000000005,
              175.06
            ],
            "arcCenter": [
              42.06,
              175.06
            ],
            "arcCenterOff": [
              0.0,
              -14.939999999999998
            ],
            "arcSense": -1
          },
          {
            "type": 1,
            "initialPos": [
              27.120000000000005,
              175.06
            ],
            "finalPos": [
              27.120000000000005,
              75.06
            ],
            "arcCenter": [
              27.120000000000005,
              175.06
            ],
            "arcCenterOff": [
              0.0,
              0.0
            ],
            "arcSense": 0
          },
          {
            "type": 3,
            "initialPos": [
              27.120000000000005,
              75.06
            ],
            "finalPos": [
              57.0,
              75.06
            ],
            "arcCenter": [
              42.06,
              75.06
            ],
            "arcCenterOff": [
              14.939999999999998,
              0.0
            ],
            "arcSense": -1
          },
          {
            "type": 1,
            "initialPos": [
              57.0,
              75.06
            ],
            "finalPos": [
              57.0,
              175.06
            ],
            "arcCenter": [
              57.0,
              75.06
            ],
            "arcCenterOff": [
              0.0,
              0.0
            ],
            "arcSense": 0
          },
          {
            "type": 3,
            "initialPos": [
              57.0,
              175.06
            ],
            "finalPos": [
              42.06,
              190.0
            ],
            "arcCenter": [
              42.06,
              175.06
            ],
            "arcCenterOff": [
              -14.939999999999998,
              0.0
            ],
            "arcSense": -1
          }
        ]
      },
      {
        "totalSegments": 7,
        "type": 1,
        "sense": -1,
        "segments": [
          {
            "type": 1,
            "initialPos": [
              27.22,
              220.36
            ],
            "finalPos": [
              28.830000000000005,
              223.15
            ],
            "arcCenter": [
              27.22,
              220.36
            ],
            "arcCenterOff": [
              0.0,
              0.0
            ],
            "arcSense": 0
          },
          {
            "type": 1,
            "initialPos": [
              28.830000000000005,
              223.15
            ],
            "finalPos": [
              35.29,
              223.15
            ],
            "arcCenter": [
              28.830000000000005,
              223.15
            ],
            "arcCenterOff": [
              0.0,
              0.0
            ],
            "arcSense": 0
          },
          {
            "type": 1,
            "initialPos": [
              35.29,
              223.15
            ],
            "finalPos": [
              38.510000000000005,
              217.56
            ],
            "arcCenter": [
              35.29,
              223.15
            ],
            "arcCenterOff": [
              0.0,
              0.0
            ],
            "arcSense": 0
          },
          {
            "type": 1,
            "initialPos": [
              38.510000000000005,
              217.56
            ],
            "finalPos": [
              35.29,
              211.97
            ],
            "arcCenter": [
              38.510000000000005,
              217.56
            ],
            "arcCenterOff": [
              0.0,
              0.0
            ],
            "arcSense": 0
          },
          {
            "type": 1,
            "initialPos": [
              35.29,
              211.97
            ],
            "finalPos": [
              28.830000000000005,
              211.97
            ],
            "arcCenter": [
              35.29,
              211.97
            ],
            "arcCenterOff": [
              0.0,
              0.0
            ],
            "arcSense": 0
          },
          {
            "type": 1,
            "initialPos": [
              28.830000000000005,
              211.97
            ],
            "finalPos": [
              25.61,
              217.56
            ],
            "arcCenter": [
              28.830000000000005,
              211.97
            ],
            "arcCenterOff": [
              0.0,
              0.0
            ],
            "arcSense": 0
          },
          {
            "type": 1,
            "initialPos": [
              25.61,
              217.56
            ],
            "finalPos": [
              27.22,
              220.36
            ],
            "arcCenter": [
              25.61,
              217.56
            ],
            "arcCenterOff": [
              0.0,
              0.0
            ],
            "arcSense": 0
          }
        ]
      },
      {
        "totalSegments": 7,
        "type": 1,
        "sense": -1,
        "segments": [
          {
            "type": 1,
            "initialPos": [
              57.22,
              220.36
            ],
            "finalPos": [
              58.83,
              223.15
            ],
            "arcCenter": [
              57.22,
              220.36
            ],
            "arcCenterOff": [
              0.0,
              0.0
            ],
            "arcSense": 0
          },
          {
            "type": 1,
            "initialPos": [
              58.83,
              223.15
            ],
            "finalPos": [
              65.29,
              223.15
            ],
            "arcCenter": [
              58.83,
              223.15
            ],
            "arcCenterOff": [
              0.0,
              0.0
            ],
            "arcSense": 0
          },
          {
            "type": 1,
            "initialPos": [
              65.29,
              223.15
            ],
            "finalPos": [
              68.51,
              217.56
            ],
            "arcCenter": [
              65.29,
              223.15
            ],
            "arcCenterOff": [
              0.0,
              0.0
            ],
            "arcSense": 0
          },
          {
            "type": 1,
            "initialPos": [
              68.51,
              217.56
            ],
            "finalPos": [
              65.29,
              211.97
            ],
            "arcCenter": [
              68.51,
              217.56
            ],
            "arcCenterOff": [
              0.0,
              0.0
            ],
            "arcSense": 0
          },
          {
            "type": 1,
            "initialPos": [
              65.29,
              211.97
            ],
            "finalPos": [
              58.83,
              211.97
            ],
            "arcCenter": [
              65.29,
              211.97
            ],
            "arcCenterOff": [
              0.0,
              0.0
            ],
            "arcSense": 0
          },
          {
            "type": 1,
            "initialPos": [
              58.83,
              211.97
            ],
            "finalPos": [
              55.61,
              217.56
            ],
            "arcCenter": [
              58.83,
              211.97
            ],
            "arcCenterOff": [
              0.0,
              0.0
            ],
            "arcSense": 0
          },
          {
            "type": 1,
            "initialPos": [
              55.61,
              217.56
            ],
            "finalPos": [
              57.22,
              220.36
            ],
            "arcCenter": [
              55.61,
              217.56
            ],
            "arcCenterOff": [
              0.0,
              0.0
            ],
            "arcSense": 0
          }
        ]
      },
      {
        "totalSegments": 15,
        "type": 1,
        "sense": -1,
        "segments": [
          {
            "type": 1,
            "initialPos": [
              111.26,
              0.0
            ],
            "finalPos": [
              107.26,
              0.0
            ],
            "arcCenter": [
              111.26,
              0.0
            ],
            "arcCenterOff": [
              0.0,
              0.0
            ],
            "arcSense": 0
          },
          {
            "type": 1,
            "initialPos": [
              107.26,
              0.0
            ],
            "finalPos": [
              26.060000000000002,
              0.0
            ],
            "arcCenter": [
              107.26,
              0.0
            ],
            "arcCenterOff": [
              0.0,
              0.0
            ],
            "arcSense": 0
          },
          {
            "type": 2,
            "initialPos": [
              26.060000000000002,
              0.0
            ],
            "finalPos": [
              21.0,
              5.06
            ],
            "arcCenter": [
              26.060000000000002,
              5.06
            ],
            "arcCenterOff": [
              0.0,
              5.06
            ],
            "arcSense": 1
          },
          {
            "type": 1,
            "initialPos": [
              21.0,
              5.06
            ],
            "finalPos": [
              21.0,
              28.06
            ],
            "arcCenter": [
              21.0,
              5.06
            ],
            "arcCenterOff": [
              0.0,
              0.0
            ],
            "arcSense": 0
          },
          {
            "type": 3,
            "initialPos": [
              21.0,
              28.06
            ],
            "finalPos": [
              16.060000000000002,
              33.0
            ],
            "arcCenter": [
              16.059999999999995,
              28.06
            ],
            "arcCenterOff": [
              -4.940000000000001,
              0.0
            ],
            "arcSense": -1
          },
          {
            "type": 1,
            "initialPos": [
              16.060000000000002,
              33.0
            ],
            "finalPos": [
              0.0,
              33.0
            ],
            "arcCenter": [
              16.060000000000002,
              33.0
            ],
            "arcCenterOff": [
              0.0,
              0.0
            ],
            "arcSense": 0
          },
          {
            "type": 1,
            "initialPos": [
              0.0,
              33.0
            ],
            "finalPos": [
              0.0,
              37.02
            ],
            "arcCenter": [
              0.0,
              33.0
            ],
            "arcCenterOff": [
              0.0,
              0.0
            ],
            "arcSense": 0
          },
          {
            "type": 1,
            "initialPos": [
              0.0,
              37.02
            ],
            "finalPos": [
              2.620000000000001,
              37.02
            ],
            "arcCenter": [
              0.0,
              37.02
            ],
            "arcCenterOff": [
              0.0,
              0.0
            ],
            "arcSense": 0
          },
          {
            "type": 3,
            "initialPos": [
              2.620000000000001,
              37.02
            ],
            "finalPos": [
              3.0,
              37.400000000000006
            ],
            "arcCenter": [
              3.0600000000000005,
              36.96
            ],
            "arcCenterOff": [
              0.4399999999999995,
              -0.060000000000002274
            ],
            "arcSense": -1
          },
          {
            "type": 1,
            "initialPos": [
              3.0,
              37.400000000000006
            ],
            "finalPos": [
              3.0,
              230.72
            ],
            "arcCenter": [
              3.0,
              37.400000000000006
            ],
            "arcCenterOff": [
              0.0,
              0.0
            ],
            "arcSense": 0
          },
          {
            "type": 3,
            "initialPos": [
              3.0,
              230.72
            ],
            "finalPos": [
              2.620000000000001,
              231.1
            ],
            "arcCenter": [
              3.0600000000000005,
              231.16
            ],
            "arcCenterOff": [
              0.0600000000000005,
              0.4399999999999977
            ],
            "arcSense": -1
          },
          {
            "type": 1,
            "initialPos": [
              2.620000000000001,
              231.1
            ],
            "finalPos": [
              0.0,
              231.1
            ],
            "arcCenter": [
              2.620000000000001,
              231.1
            ],
            "arcCenterOff": [
              0.0,
              0.0
            ],
            "arcSense": 0
          },
          {
            "type": 1,
            "initialPos": [
              0.0,
              231.1
            ],
            "finalPos": [
              0.0,
              235.12
            ],
            "arcCenter": [
              0.0,
              231.1
            ],
            "arcCenterOff": [
              0.0,
              0.0
            ],
            "arcSense": 0
          },
          {
            "type": 1,
            "initialPos": [
              0.0,
              235.12
            ],
            "finalPos": [
              107.32000000000001,
              235.12
            ],
            "arcCenter": [
              0.0,
              235.12
            ],
            "arcCenterOff": [
              0.0,
              0.0
            ],
            "arcSense": 0
          },
          {
            "type": 1,
            "initialPos": [
              107.32000000000001,
              235.12
            ],
            "finalPos": [
              107.32000000000001,
              0.05999999999999961
            ],
            "arcCenter": [
              107.32000000000001,
              235.12
            ],
            "arcCenterOff": [
              0.0,
              0.0
            ],
            "arcSense": 0
          }
        ]
      }
    ],
    "voronoi": [
      [
        1.1247209276844998,
        233.1099999999992
      ],
      [
        1.231656959227431,
        233.1907572063241
      ],
      [
        1.4003079251074837,
        233.32013248684495
      ],
      [
        1.5680565622496747,
        233.4508471309516
      ],
      [
        1.7372517953452729,
        233.58475356540742
      ],
      [
        1.9103447306371262,
        233.72385607619944
      ],
      [
        2.0900335197679034,
        233.87043237945207
      ],
      [
        2.2794406897478705,
        234.02718834202082
      ],
      [
        2.482349323305918,
        234.19746939947643
      ],
      [
        2.7035391004410005,
        234.38556602153005
      ],
      [
        2.9492908991052538,
        234.59717637369337
      ],
      [
        3.2281820080062946,
        234.840138820037
      ],
      [
        55.396393186363085,
        233.551768390366
      ],
      [
        55.55200021291519,
        229.46926856006553
      ],
      [
        55.710704312810066,
        225.34151192886912
      ],
      [
        55.874559736386814,
        221.11599225666674
      ],
      [
        56.045858419006564,
        216.7352046376963
      ],
      [
        56.2272640764577,
        212.13334418195467
      ],
      [
        56.42198904237067,
        207.23202196294997
      ],
      [
        56.634040329233216,
        201.9343637653252
      ],
      [
        56.868577545409096,
        196.11647698286026
      ],
      [
        57.132454813433014,
        189.61457384088783
      ],
      [
        57.43507463485757,
        182.20471918725553
      ],
      [
        57.78979215464972,
        173.56955576460976
      ],
      [
        58.21633998735831,
        163.2408750969857
      ],
      [
        58.74526455406489,
        150.49457380137864
      ],
      [
        59.37808421452017,
        135.30948941254496
      ],
      [
        61.611568151821814,
        134.32376423253004
      ],
      [
        64.20824689982955,
        133.17944568248038
      ],
      [
        66.80744927974528,
        132.0357146674826
      ],
      [
        69.41242180646358,
        130.89114603183745
      ],
      [
        72.02643854685371,
        129.74430778603394
      ],
      [
        74.65281759289357,
        128.59375393030237
      ],
      [
        77.29493799784116,
        127.43801711570919
      ],
      [
        79.95625736105433,
        126.27560106295482
      ],
      [
        82.64033025863495,
        125.10497265430246
      ],
      [
        85.3508277334441,
        123.9245536077758
      ],
      [
        88.0915580774991,
        122.73271163478918
      ],
      [
        90.86648916535154,
        121.52775097196918
      ],
      [
        93.67977262761737,
        120.3079021657319
      ],
      [
        96.53577019091676,
        119.07131097246148
      ],
      [
        99.43908255603361,
        117.81602621899789
      ],
      [
        99.96259303474486,
        117.58999999999999
      ],
      [
        71.3119152032625,
        36.00808479676749
      ],
      [
        71.15682857376353,
        35.5430462255762
      ],
      [
        70.68335353367675,
        34.1176158312484
      ],
      [
        70.2223820990293,
        32.724185474965196
      ],
      [
        69.77291655406484,
        31.359925679603965
      ],
      [
        69.33403105252151,
        30.0221987540498
      ],
      [
        68.90486363344783,
        28.70853660089548
      ],
      [
        66.65999999999998,
        21.80754098360655
      ],
      [
        37.55999999999999,
        16.559999999999985
      ],
      [
        26.05999999999925,
        5.059999999999564
      ],
      [
        26.06000000000006,
        5.059999999999783
      ],
      [
        26.059999999999512,
        5.060000000015745
      ],
      [
        26.059999999997288,
        5.059999999969567
      ],
      [
        26.06000000000006,
        5.0600000000000405
      ],
      [
        26.05999999999996,
        5.06000000000019
      ],
      [
        26.06000000000003,
        5.060000000000085
      ],
      [
        26.06000000000317,
        5.059999999992601
      ],
      [
        26.05999999999949,
        5.060000000018415
      ],
      [
        26.060000000002937,
        5.060000000046345
      ],
      [
        26.059999999970962,
        5.059999999964506
      ],
      [
        26.060000000000052,
        5.060000000005629
      ],
      [
        26.05999999999355,
        5.059999999971253
      ],
      [
        26.059999999998098,
        5.060000000001319
      ],
      [
        26.059999999948374,
        5.05999999995776
      ],
      [
        26.060000000012323,
        5.060000000046345
      ],
      [
        26.059999999998425,
        5.060000000000948
      ],
      [
        26.06000000000018,
        5.060000000001973
      ],
      [
        26.05999999999989,
        5.059999999999664
      ],
      [
        26.06000000001017,
        5.059999999992958
      ],
      [
        26.059999999948374,
        5.05999999995776
      ],
      [
        26.05999999999883,
        5.059999999990217
      ],
      [
        26.059999999985138,
        5.059999999942886
      ],
      [
        26.05999999998592,
        5.060000000032853
      ],
      [
        26.05999999998005,
        5.059999999958925
      ],
      [
        26.05999999998592,
        5.060000000032853
      ],
      [
        26.059999999995306,
        5.059999999988688
      ],
      [
        26.05999999998005,
        5.059999999958925
      ],
      [
        26.060000000076265,
        5.059999999984746
      ],
      [
        26.05999999997497,
        5.06
      ],
      [
        26.059999999948374,
        5.0599999999953065
      ],
      [
        26.05999999999998,
        5.060000000000005
      ],
      [
        26.0600000000034,
        5.060000000000369
      ],
      [
        26.0599999999992,
        5.060000000001257
      ],
      [
        26.05999999999002,
        5.059999999991972
      ],
      [
        26.059999999981223,
        5.059999999993738
      ],
      [
        26.06000000003521,
        5.060000000017994
      ],
      [
        26.06000000002347,
        5.060000000032853
      ],
      [
        26.060000000001175,
        5.059999999984746
      ],
      [
        26.059999999999064,
        5.0599999999971805
      ],
      [
        26.060000000061017,
        5.0599999999953065
      ],
      [
        26.06000000003521,
        5.060000000017994
      ],
      [
        26.059999999948374,
        5.0599999999953065
      ],
      [
        3.2281820080762635,
        33.27986117995908
      ],
      [
        2.949290898897706,
        33.522823626391016
      ],
      [
        2.7035391004737352,
        33.734433978410934
      ],
      [
        2.4823493233532776,
        33.92253060049455
      ],
      [
        2.279440689779113,
        34.09281165798446
      ],
      [
        2.0900335197564033,
        34.249567620590774
      ],
      [
        1.910344730705912,
        34.39614392376409
      ],
      [
        1.7372517953511224,
        34.535246434589624
      ],
      [
        1.568056562264422,
        34.66915286903592
      ],
      [
        1.400307925100467,
        34.799867513204106
      ],
      [
        1.2316569592483013,
        34.929242793656776
      ],
      [
        1.1247209276838586,
        35.010000000000026
      ],
      [
        1.1422564984761348,
        35.13751530416758
      ],
      [
        1.1806317887277746,
        35.43378669602466
      ],
      [
        1.210749668670747,
        35.68341846092588
      ],
      [
        1.2347212121215154,
        35.89950265124317
      ],
      [
        1.2539565504063575,
        36.09098779419696
      ],
      [
        1.269425808426245,
        36.2642590564045
      ],
      [
        1.2818098125994233,
        36.42406058246516
      ],
      [
        1.2915908128914513,
        36.574062780615016
      ],
      [
        1.2991087137031307,
        36.717229285901986
      ],
      [
        1.3045964060004351,
        36.85606760655411
      ],
      [
        1.3082016962735512,
        36.99281192779246
      ],
      [
        1.3082016962762424,
        231.12718807205897
      ],
      [
        1.304596406000277,
        231.26393239333294
      ],
      [
        1.2991087137021413,
        231.40277071419493
      ],
      [
        1.2915908128967182,
        231.54593721929788
      ],
      [
        1.2818098125993522,
        231.69593941761596
      ],
      [
        1.2694258084243781,
        231.85574094357523
      ],
      [
        1.2539565504100185,
        232.02901220593975
      ],
      [
        1.2347212121620093,
        232.22049734866107
      ],
      [
        1.2107496686681571,
        232.43658153920168
      ],
      [
        1.1806317887225237,
        232.68621330396027
      ],
      [
        1.1422564985047163,
        232.9824846955979
      ],
      [
        58.77552628554362,
        135.26502354991834
      ],
      [
        58.936904256032264,
        135.27686730930444
      ],
      [
        97.94673627357287,
        111.98161300228227
      ],
      [
        95.72687210151425,
        105.79516156488046
      ],
      [
        93.72547666442209,
        100.20753664290588
      ],
      [
        91.91008659630407,
        95.1296210466894
      ],
      [
        90.25433934484407,
        90.48903757156879
      ],
      [
        88.73660268023066,
        86.22638824018951
      ],
      [
        87.33895769003045,
        82.29246352506847
      ],
      [
        86.04643326992684,
        78.64614168513178
      ],
      [
        84.8464224193973,
        75.25278698040259
      ],
      [
        83.728231880966,
        72.08301378435216
      ],
      [
        82.68273088304836,
        69.11172263721988
      ],
      [
        81.70207443849311,
        66.31734087936397
      ],
      [
        80.77948336227593,
        63.681218920037736
      ],
      [
        79.9090678869887,
        61.18714613529313
      ],
      [
        79.0856851124601,
        58.820959602869124
      ],
      [
        78.30482294695042,
        56.57022552514458
      ],
      [
        77.56250496319588,
        54.42397803684091
      ],
      [
        76.85521189464357,
        52.372503667098044
      ],
      [
        76.17981646689978,
        50.40716238631264
      ],
      [
        75.53352898839674,
        48.52023816847064
      ],
      [
        74.91385167721194,
        46.70481351682989
      ],
      [
        74.31854012380313,
        44.95466356106989
      ],
      [
        73.74557061525492,
        43.26416622819288
      ],
      [
        73.19311229979719,
        41.628225683662045
      ],
      [
        72.65950336793325,
        40.042206781942845
      ],
      [
        72.14323058245002,
        38.50187869278971
      ],
      [
        71.64291161261231,
        37.003366207603065
      ],
      [
        16.38960724252999,
        54.91746611694735
      ],
      [
        15.4919166203953,
        52.268573736452964
      ],
      [
        14.324337684723771,
        48.813109353033816
      ],
      [
        13.497438496905792,
        46.35709482724707
      ],
      [
        12.875265174881639,
        44.501351247371986
      ],
      [
        12.3854414478638,
        43.03331278636449
      ],
      [
        11.985847662989029,
        41.82921604718677
      ],
      [
        11.650261267501806,
        40.81194754976702
      ],
      [
        11.361459310823376,
        39.9307943757696
      ],
      [
        11.107617979981962,
        39.1508721681395
      ],
      [
        10.880304393218369,
        38.44722621702121
      ],
      [
        10.673293498466558,
        37.80135355798957
      ],
      [
        10.481837553423569,
        37.19905231352121
      ],
      [
        10.302195511752666,
        36.629032326334126
      ],
      [
        10.131317103589234,
        36.081977730188896
      ],
      [
        9.966621246929007,
        35.54988355170721
      ],
      [
        9.80583238885322,
        35.02555848624272
      ],
      [
        9.646851502157672,
        34.50222409836061
      ],
      [
        9.48764560468703,
        33.97316102309188
      ],
      [
        9.326143198155018,
        33.431362130407564
      ],
      [
        32.32555202674225,
        134.05999999999963
      ],
      [
        32.325552026754856,
        134.0600000000004
      ],
      [
        40.78892848590898,
        134.05999999999938
      ],
      [
        40.78892848597416,
        134.0600000000041
      ],
      [
        42.10937403120618,
        134.05999999999997
      ],
      [
        44.03433625211398,
        134.19640531589465
      ],
      [
        46.8983231317874,
        134.40101584977978
      ],
      [
        49.52635860755963,
        134.5902832241634
      ],
      [
        49.81521220841543,
        134.6110390250738
      ],
      [
        52.790088393585535,
        134.82649796718295
      ],
      [
        55.8286607356155,
        135.04828527885994
      ],
      [
        22.02055902610902,
        71.94692638874062
      ],
      [
        20.367463305741374,
        66.90169903429971
      ],
      [
        20.25098081000587,
        66.5483178323583
      ],
      [
        19.06370095010829,
        62.94017349311069
      ],
      [
        18.006939395206963,
        59.7503480332952
      ],
      [
        17.271231604712767,
        57.546326802671715
      ],
      [
        17.13047838814319,
        57.12367093200808
      ],
      [
        24.251081948481584,
        134.06000000000034
      ],
      [
        16.446991305116413,
        134.0599999999964
      ],
      [
        16.446991305075713,
        134.060000000006
      ],
      [
        8.809011474012786,
        134.05999999998974
      ],
      [
        8.809011473835769,
        134.05999999999895
      ],
      [
        24.25108194849384,
        134.06000000000535
      ],
      [
        26.453627794409755,
        85.57831394099433
      ],
      [
        27.19258986577392,
        87.85303368589743
      ],
      [
        31.60321769496217,
        101.4803989536107
      ],
      [
        38.77141622576598,
        123.6932776271367
      ],
      [
        24.19470866179894,
        78.61711485444823
      ],
      [
        26.05999999997067,
        5.06
      ],
      [
        26.060000000008664,
        5.060000000002417
      ],
      [
        26.060000000002574,
        5.060000000000245
      ],
      [
        26.05999999999974,
        5.060000000000033
      ],
      [
        26.060000000001864,
        5.0600000000008825
      ],
      [
        26.05999999998246,
        5.05999999999248
      ],
      [
        26.059999999989046,
        5.060000000002192
      ],
      [
        26.059999999926085,
        5.059999999984746
      ],
      [
        26.060000000000002,
        5.059999999987482
      ],
      [
        26.060000000061017,
        5.0599999999953065
      ],
      [
        26.05999999997067,
        5.059999999987093
      ],
      [
        26.059999999968895,
        5.059999999991196
      ],
      [
        26.060000000136107,
        5.060000000014079
      ],
      [
        26.05999999991083,
        5.060000000014079
      ],
      [
        26.059999999984974,
        5.059999999997495
      ],
      [
        26.06000000001017,
        5.059999999999218
      ],
      [
        26.05999999991083,
        5.05999999998592
      ],
      [
        26.059999999805235,
        5.05999999995072
      ],
      [
        26.060000000007634,
        5.060000000000978
      ],
      [
        26.05999999998592,
        5.0599999999953065
      ]
    ],
    "polyShape": {
      "type": "Polygon",
      "coordinates": [
        [
          [
            25.935821383674067,
            0.001523977397206444
          ],
          [
            25.811717567903266,
            0.00609499160182736
          ],
          [
            25.687763308185687,
            0.013710289205827841
          ],
          [
            25.564033269932423,
            0.02436528303868357
          ],
          [
            25.440601983491966,
            0.03805355493052698
          ],
          [
            25.317543799255866,
            0.05476685957820848
          ],
          [
            25.194932842872873,
            0.07449512951195825
          ],
          [
            25.072842970598394,
            0.09722648115965438
          ],
          [
            24.95134772480624,
            0.12294722200504626
          ],
          [
            24.83052028968949,
            0.15164185883560766
          ],
          [
            24.710433447177017,
            0.18329310707507407
          ],
          [
            24.591159533092423,
            0.2178819011950237
          ],
          [
            24.472770393581612,
            0.25538740619923406
          ],
          [
            24.355337341835373,
            0.2957870301739147
          ],
          [
            24.238931115132964,
            0.33905643789622086
          ],
          [
            24.123621832232644,
            0.38516956549289016
          ],
          [
            24.009478951134753,
            0.4340986361401358
          ],
          [
            23.896571227242774,
            0.48581417679537786
          ],
          [
            23.784966671947693,
            0.540285035950693
          ],
          [
            23.67473251166045,
            0.5974784023973241
          ],
          [
            23.565935147317298,
            0.6573598249899204
          ],
          [
            23.4586401143823,
            0.7198932333986239
          ],
          [
            23.35291204337129,
            0.7850409598364818
          ],
          [
            23.248814620920818,
            0.852763761749121
          ],
          [
            23.146410551425703,
            0.923020845452986
          ],
          [
            23.04576151926829,
            0.995769890707936
          ],
          [
            22.94692815166203,
            1.0709670762093735
          ],
          [
            22.849969982131952,
            1.1485671059845526
          ],
          [
            22.75494541465389,
            1.2285232366771899
          ],
          [
            22.661911688474092,
            1.310787305703908
          ],
          [
            22.570924843630443,
            1.3953097602655786
          ],
          [
            22.48203968719607,
            1.4820396871960702
          ],
          [
            22.395309760265576,
            1.5709248436304408
          ],
          [
            22.31078730570391,
            1.6619116884740857
          ],
          [
            22.22852323667719,
            1.7549454146538883
          ],
          [
            22.148567105984554,
            1.849969982131955
          ],
          [
            22.07096707620937,
            1.9469281516620294
          ],
          [
            21.99576989070794,
            2.0457615192682868
          ],
          [
            21.92302084545299,
            2.146410551425702
          ],
          [
            21.852763761749124,
            2.2488146209208137
          ],
          [
            21.785040959836486,
            2.3529120433712896
          ],
          [
            21.719893233398622,
            2.458640114382299
          ],
          [
            21.657359824989925,
            2.565935147317293
          ],
          [
            21.59747840239733,
            2.6747325116604523
          ],
          [
            21.540285035950696,
            2.78496667194769
          ],
          [
            21.48581417679538,
            2.896571227242771
          ],
          [
            21.434098636140135,
            3.009478951134752
          ],
          [
            21.385169565492888,
            3.1236218322326463
          ],
          [
            21.339056437896225,
            3.238931115132959
          ],
          [
            21.29578703017392,
            3.3553373418353685
          ],
          [
            21.255387406199233,
            3.4727703935816097
          ],
          [
            21.217881901195028,
            3.591159533092422
          ],
          [
            21.183293107075073,
            3.7104334471770146
          ],
          [
            21.15164185883561,
            3.8305202896894857
          ],
          [
            21.122947222005045,
            3.951347724806239
          ],
          [
            21.09722648115966,
            4.07284297059839
          ],
          [
            21.07449512951196,
            4.194932842872874
          ],
          [
            21.05476685957821,
            4.31754379925587
          ],
          [
            21.038053554930528,
            4.440601983491967
          ],
          [
            21.024365283038684,
            4.564033269932422
          ],
          [
            21.013710289205832,
            4.687763308185684
          ],
          [
            21.006094991601827,
            4.811717567903266
          ],
          [
            21.001523977397213,
            4.935821383674065
          ],
          [
            21.0,
            5.06
          ],
          [
            21.0,
            28.06
          ],
          [
            20.998512164359248,
            28.181233668903186
          ],
          [
            20.994049553653554,
            28.30239431117744
          ],
          [
            20.986614855992727,
            28.42340894418236
          ],
          [
            20.976212549760653,
            28.544204673228027
          ],
          [
            20.962848900917628,
            28.66470873548413
          ],
          [
            20.94653195922602,
            28.784848543809485
          ],
          [
            20.92727155340137,
            28.904551730475884
          ],
          [
            20.90507928519196,
            29.02374619075967
          ],
          [
            20.879968522390328,
            29.142360126374935
          ],
          [
            20.851954390781046,
            29.260322088722123
          ],
          [
            20.821053765029475,
            29.377561021925995
          ],
          [
            20.787285258517116,
            29.49400630563704
          ],
          [
            20.7506692121296,
            29.609587797570523
          ],
          [
            20.71122768200412,
            29.724235875757568
          ],
          [
            20.66898442624361,
            29.83788148048284
          ],
          [
            20.623964890605755,
            29.95045615588354
          ],
          [
            20.57619619317544,
            30.06189209118465
          ],
          [
            20.525707108029813,
            30.17212216154559
          ],
          [
            20.472528047905847,
            30.281079968493753
          ],
          [
            20.416691045880874,
            30.388699879920427
          ],
          [
            20.358229736077035,
            30.49491706961513
          ],
          [
            20.297179333401346,
            30.59966755631451
          ],
          [
            20.23357661233355,
            30.702888242242256
          ],
          [
            20.167459884774573,
            30.804516951116835
          ],
          [
            20.098868976968824,
            30.904492465604154
          ],
          [
            20.02784520551439,
            31.002754564192617
          ],
          [
            19.95443135247544,
            31.099244057468294
          ],
          [
            19.878671639611923,
            31.193902823768408
          ],
          [
            19.800611701742035,
            31.286673844191657
          ],
          [
            19.7202985592535,
            31.377501236944273
          ],
          [
            19.63778058978025,
            31.46633029100111
          ],
          [
            19.553107499061547,
            31.553107499061543
          ],
          [
            19.466330291001107,
            31.637780589780245
          ],
          [
            19.37750123694427,
            31.720298559253497
          ],
          [
            19.286673844191654,
            31.80061170174203
          ],
          [
            19.19390282376841,
            31.87867163961192
          ],
          [
            19.099244057468297,
            31.954431352475435
          ],
          [
            19.00275456419262,
            32.02784520551439
          ],
          [
            18.904492465604157,
            32.098868976968824
          ],
          [
            18.804516951116838,
            32.16745988477457
          ],
          [
            18.70288824224226,
            32.23357661233356
          ],
          [
            18.599667556314515,
            32.297179333401346
          ],
          [
            18.494917069615134,
            32.358229736077035
          ],
          [
            18.38869987992043,
            32.416691045880874
          ],
          [
            18.281079968493756,
            32.47252804790585
          ],
          [
            18.172122161545595,
            32.52570710802981
          ],
          [
            18.061892091184653,
            32.57619619317544
          ],
          [
            17.950456155883543,
            32.62396489060576
          ],
          [
            17.837881480482842,
            32.66898442624361
          ],
          [
            17.724235875757564,
            32.71122768200412
          ],
          [
            17.609587797570526,
            32.7506692121296
          ],
          [
            17.494006305637043,
            32.787285258517116
          ],
          [
            17.377561021926,
            32.821053765029475
          ],
          [
            17.260322088722127,
            32.85195439078105
          ],
          [
            17.14236012637494,
            32.879968522390335
          ],
          [
            17.023746190759674,
            32.90507928519196
          ],
          [
            16.904551730475887,
            32.927271553401376
          ],
          [
            16.78484854380949,
            32.94653195922602
          ],
          [
            16.664708735484126,
            32.96284890091763
          ],
          [
            16.54420467322803,
            32.97621254976065
          ],
          [
            16.423408944182356,
            32.986614855992734
          ],
          [
            16.302394311177444,
            32.994049553653554
          ],
          [
            16.18123366890319,
            32.998512164359255
          ],
          [
            16.060000000000002,
            33.0
          ],
          [
            0.0,
            33.0
          ],
          [
            0.0,
            37.02
          ],
          [
            2.620000000000001,
            37.02
          ],
          [
            2.6166659627610116,
            36.985591628032985
          ],
          [
            2.61601857444872,
            36.95102816822201
          ],
          [
            2.6180617583015167,
            36.91651907861542
          ],
          [
            2.622783132419423,
            36.88227348777265
          ],
          [
            2.6301540847996616,
            36.84849892742407
          ],
          [
            2.6401299467282637,
            36.815400074807805
          ],
          [
            2.6526502634769837,
            36.78317751230506
          ],
          [
            2.66763916066504,
            36.75202651189066
          ],
          [
            2.685005804065506,
            36.72213585176525
          ],
          [
            2.704644950069877,
            36.69368667234034
          ],
          [
            2.72643758347494,
            36.66685137850919
          ],
          [
            2.7502516387268905,
            36.64179259485577
          ],
          [
            2.7759428002518973,
            36.61866218013343
          ],
          [
            2.803355377023017,
            36.597600306985505
          ],
          [
            2.832323246063501,
            36.578734612485036
          ],
          [
            2.8626708591687695,
            36.5621794246412
          ],
          [
            2.8942143067462176,
            36.548035069560086
          ],
          [
            2.9267624323258676,
            36.53638726345838
          ],
          [
            2.960117990987845,
            36.52730659321444
          ],
          [
            2.994078844686449,
            36.52084808860472
          ],
          [
            3.028439187227084,
            36.517050888817785
          ],
          [
            3.0629907914725294,
            36.51593800526687
          ],
          [
            3.0975242712203617,
            36.5175161821384
          ],
          [
            3.1318303501044404,
            36.52177585552155
          ],
          [
            3.165701129830767,
            36.5286912113665
          ],
          [
            3.198931350062095,
            36.53822034192019
          ],
          [
            3.2313196323162394,
            36.550305499691504
          ],
          [
            3.262669700339977,
            36.5648734474069
          ],
          [
            3.2927915695629117,
            36.581835901835674
          ],
          [
            3.321502698423105,
            36.6010900687952
          ],
          [
            3.3486290945873307,
            36.62251926609405
          ],
          [
            3.374006369362151,
            36.64599363063785
          ],
          [
            3.3974807339059474,
            36.671370905412665
          ],
          [
            3.4189099312047997,
            36.69849730157689
          ],
          [
            3.4381640981643216,
            36.72720843043709
          ],
          [
            3.4551265525930948,
            36.75733029966002
          ],
          [
            3.4696945003084956,
            36.78868036768376
          ],
          [
            3.4817796580798124,
            36.82106864993791
          ],
          [
            3.4913087886335017,
            36.85429887016923
          ],
          [
            3.4982241444784545,
            36.88816964989556
          ],
          [
            3.502483817861604,
            36.92247572877964
          ],
          [
            3.5040619947331315,
            36.95700920852747
          ],
          [
            3.5029491111822146,
            36.99156081277292
          ],
          [
            3.4991519113952787,
            37.02592115531355
          ],
          [
            3.4926934067855626,
            37.059882009012156
          ],
          [
            3.483612736541623,
            37.09323756767413
          ],
          [
            3.471964930439915,
            37.12578569325378
          ],
          [
            3.457820575358804,
            37.15732914083123
          ],
          [
            3.441265387514969,
            37.1876767539365
          ],
          [
            3.4223996930144995,
            37.216644622976986
          ],
          [
            3.4013378198665762,
            37.244057199748106
          ],
          [
            3.378207405144229,
            37.26974836127311
          ],
          [
            3.3531486214908117,
            37.29356241652506
          ],
          [
            3.3263133276596584,
            37.31535504993012
          ],
          [
            3.2978641482347495,
            37.33499419593449
          ],
          [
            3.267973488109339,
            37.35236083933496
          ],
          [
            3.236822487694946,
            37.36734973652302
          ],
          [
            3.2045999251921984,
            37.37987005327174
          ],
          [
            3.171501072575934,
            37.38984591520034
          ],
          [
            3.137726512227351,
            37.397216867580575
          ],
          [
            3.1034809213845804,
            37.40193824169849
          ],
          [
            3.0689718317779953,
            37.40398142555128
          ],
          [
            3.03440837196702,
            37.40333403723899
          ],
          [
            3.0,
            37.4
          ],
          [
            3.0,
            230.72
          ],
          [
            3.03440837196702,
            230.716665962761
          ],
          [
            3.0689718317779935,
            230.71601857444873
          ],
          [
            3.1034809213845787,
            230.7180617583015
          ],
          [
            3.137726512227351,
            230.7227831324194
          ],
          [
            3.171501072575932,
            230.73015408479966
          ],
          [
            3.2045999251921966,
            230.74012994672827
          ],
          [
            3.236822487694944,
            230.752650263477
          ],
          [
            3.267973488109339,
            230.76763916066503
          ],
          [
            3.2978641482347477,
            230.7850058040655
          ],
          [
            3.3263133276596566,
            230.80464495006987
          ],
          [
            3.35314862149081,
            230.82643758347493
          ],
          [
            3.3782074051442272,
            230.8502516387269
          ],
          [
            3.4013378198665745,
            230.8759428002519
          ],
          [
            3.422399693014496,
            230.90335537702302
          ],
          [
            3.4412653875149672,
            230.9323232460635
          ],
          [
            3.4578205753588005,
            230.96267085916878
          ],
          [
            3.4719649304399116,
            230.99421430674622
          ],
          [
            3.4836127365416196,
            231.02676243232585
          ],
          [
            3.492693406785561,
            231.06011799098783
          ],
          [
            3.499151911395277,
            231.09407884468644
          ],
          [
            3.502949111182213,
            231.1284391872271
          ],
          [
            3.5040619947331297,
            231.16299079147254
          ],
          [
            3.5024838178616022,
            231.19752427122035
          ],
          [
            3.4982241444784528,
            231.23183035010445
          ],
          [
            3.4913087886335,
            231.26570112983077
          ],
          [
            3.4817796580798106,
            231.2989313500621
          ],
          [
            3.469694500308494,
            231.33131963231622
          ],
          [
            3.455126552593093,
            231.36266970033998
          ],
          [
            3.4381640981643216,
            231.39279156956292
          ],
          [
            3.418909931204798,
            231.4215026984231
          ],
          [
            3.3974807339059456,
            231.44862909458732
          ],
          [
            3.3740063693621494,
            231.47400636936214
          ],
          [
            3.3486290945873307,
            231.49748073390595
          ],
          [
            3.321502698423103,
            231.5189099312048
          ],
          [
            3.2927915695629117,
            231.53816409816432
          ],
          [
            3.262669700339977,
            231.5551265525931
          ],
          [
            3.2313196323162376,
            231.5696945003085
          ],
          [
            3.198931350062093,
            231.5817796580798
          ],
          [
            3.165701129830767,
            231.59130878863348
          ],
          [
            3.1318303501044404,
            231.59822414447845
          ],
          [
            3.0975242712203617,
            231.6024838178616
          ],
          [
            3.0629907914725294,
            231.60406199473312
          ],
          [
            3.028439187227086,
            231.6029491111822
          ],
          [
            2.994078844686449,
            231.59915191139527
          ],
          [
            2.960117990987845,
            231.59269340678554
          ],
          [
            2.9267624323258694,
            231.58361273654162
          ],
          [
            2.8942143067462176,
            231.57196493043992
          ],
          [
            2.8626708591687695,
            231.5578205753588
          ],
          [
            2.8323232460635026,
            231.54126538751495
          ],
          [
            2.803355377023017,
            231.52239969301448
          ],
          [
            2.7759428002518973,
            231.50133781986656
          ],
          [
            2.7502516387268905,
            231.47820740514422
          ],
          [
            2.726437583474942,
            231.4531486214908
          ],
          [
            2.704644950069879,
            231.42631332765964
          ],
          [
            2.685005804065508,
            231.39786414823473
          ],
          [
            2.6676391606650416,
            231.36797348810933
          ],
          [
            2.6526502634769855,
            231.33682248769495
          ],
          [
            2.6401299467282655,
            231.30459992519218
          ],
          [
            2.6301540847996634,
            231.27150107257592
          ],
          [
            2.622783132419425,
            231.23772651222734
          ],
          [
            2.6180617583015184,
            231.20348092138457
          ],
          [
            2.616018574448722,
            231.16897183177798
          ],
          [
            2.6166659627610134,
            231.13440837196703
          ],
          [
            2.6200000000000028,
            231.1
          ],
          [
            0.0,
            231.1
          ],
          [
            0.0,
            235.12
          ],
          [
            107.32000000000001,
            235.12
          ],
          [
            107.32000000000001,
            0.05999999999999961
          ],
          [
            111.26,
            0.0
          ],
          [
            107.26,
            0.0
          ],
          [
            26.060000000000002,
            0.0
          ],
          [
            25.935821383674067,
            0.001523977397206444
          ]
        ]
      ]
    }
  }
}